csvsdataset/__init__.py
csvsdataset/csvsdataset.py
csvsdataset/whereami.py
csvsdataset/testdata/__init__.py
csvsdataset/testdata/test_data_0.csv
csvsdataset/testdata/test_data_1.csv
csvsdataset/testdata/test_data_2.csv
csvsdataset/testdata/test_data_3.csv
csvsdataset-0.0.7.dist-info/LICENSE
csvsdataset-0.0.7.dist-info/METADATA
csvsdataset-0.0.7.dist-info/WHEEL
csvsdataset-0.0.7.dist-info/entry_points.txt
csvsdataset-0.0.7.dist-info/top_level.txt
csvsdataset-0.0.7.dist-info/RECORD
