Metadata-Version: 2.1
Name: csvsdataset
Version: 0.0.7
Summary: Memory frugal torch dataset from a csv collection
Home-page: https://github.com/microprediction/csvsdataset
Author: microprediction
Author-email: peter.cotton@microprediction.com
License: MIT
Classifier: License :: OSI Approved :: MIT License
Classifier: Programming Language :: Python :: 3
Classifier: Programming Language :: Python :: 3.8
Classifier: Programming Language :: Python :: 3.9
License-File: LICENSE
Requires-Dist: numpy
Requires-Dist: torch
Requires-Dist: pandas
